smerch/__init__.py
smerch-0.0.1.dist-info/METADATA
smerch-0.0.1.dist-info/WHEEL
smerch-0.0.1.dist-info/RECORD
