Metadata-Version: 2.3
Name: smerch
Version: 0.0.1
Summary: 
Author: joegasewicz
Author-email: joegasewicz@gmail.com
Requires-Python: >=3.14
Classifier: Programming Language :: Python :: 3
Requires-Dist: setuptools (>=80.9.0,<81.0.0)
